{"version":1,"resource":"vscode-remote://ssh-remote%2Bs_01jb9hn6ht245n1ffwywe6mtvk@ssh.lightning.ai/teamspace/studios/this_studio/Extraction.py","entries":[{"id":"mphF.py","timestamp":1734375733333},{"id":"YYsp.py","timestamp":1734375757761},{"id":"sIcJ.py","timestamp":1734375775481},{"id":"0vQC.py","timestamp":1734375868884},{"id":"XOzR.py","timestamp":1734375882808},{"id":"1HHz.py","timestamp":1734375911500},{"id":"dgCZ.py","timestamp":1734375921792},{"id":"gTts.py","source":"undoRedo.source","timestamp":1734375930720},{"id":"jYTP.py","timestamp":1734375948460},{"id":"XCfj.py","timestamp":1734376040559},{"id":"Awro.py","timestamp":1734376079095},{"id":"wqjo.py","timestamp":1734376323159},{"id":"40pV.py","timestamp":1734376431746},{"id":"BQQj.py","timestamp":1734376454378},{"id":"IDWZ.py","timestamp":1734376470150},{"id":"clII.py","timestamp":1734376485762},{"id":"hWz0.py","timestamp":1734377194686},{"id":"hfPC.py","timestamp":1734377207906},{"id":"0V0d.py","timestamp":1734377279782},{"id":"Ah4z.py","timestamp":1734377323969},{"id":"0XLS.py","timestamp":1734377408657},{"id":"JXnk.py","source":"renamed.source","sourceDescription":"~/Crawler.py","timestamp":1734380099843}]}